{
  "src/analyzer.py": {
    "mtime_ns": 1768390185412688224,
    "size": 46781,
    "sha256_12": "374b26842cf6"
  },
  "src/catalog.py": {
    "mtime_ns": 1768360032139292720,
    "size": 13843,
    "sha256_12": "1f52f9d1d4a7"
  },
  "src/craft_recipes.py": {
    "mtime_ns": 1768318601829451223,
    "size": 28228,
    "sha256_12": "5ff8c02ec0af"
  },
  "src/engine.py": {
    "mtime_ns": 1768390185586687441,
    "size": 13328,
    "sha256_12": "34d033fc84a4"
  },
  "src/utils.py": {
    "mtime_ns": 1768189967749259190,
    "size": 1040,
    "sha256_12": "ffc01cb3d8f3"
  },
  "src/webcraft/__init__.py": {
    "mtime_ns": 1768353714949547449,
    "size": 252,
    "sha256_12": "f9cfb37ca166"
  },
  "src/webcraft/api.py": {
    "mtime_ns": 1768447643254983805,
    "size": 15377,
    "sha256_12": "5a9e1b935cb9"
  },
  "src/webcraft/app.py": {
    "mtime_ns": 1768447643255983801,
    "size": 4751,
    "sha256_12": "50bc4d1a86ed"
  },
  "src/webcraft/catalog_store.py": {
    "mtime_ns": 1768392925093314033,
    "size": 19521,
    "sha256_12": "0ae808cd1cbe"
  },
  "src/webcraft/cooking_planner.py": {
    "mtime_ns": 1768356636465472996,
    "size": 4276,
    "sha256_12": "bd00afb78bbe"
  },
  "src/webcraft/icon_service.py": {
    "mtime_ns": 1768373324307342716,
    "size": 7535,
    "sha256_12": "89e06a383a81"
  },
  "src/webcraft/planner.py": {
    "mtime_ns": 1768353714947547458,
    "size": 3808,
    "sha256_12": "a9ac339eaf54"
  },
  "src/webcraft/settings.py": {
    "mtime_ns": 1768353714948547454,
    "size": 790,
    "sha256_12": "b2f5722e0c36"
  },
  "src/webcraft/ui.py": {
    "mtime_ns": 1768447643258983787,
    "size": 75427,
    "sha256_12": "d29016022349"
  },
  ".gitignore": {
    "mtime_ns": 1768208171863591123,
    "size": 299,
    "sha256_12": "f97f702d84fd"
  },
  "conf/samples/parse_other_data.json": {
    "mtime_ns": 1768274528957962193,
    "size": 2204,
    "sha256_12": "6091b29bdccc"
  },
  "conf/settings.ini": {
    "mtime_ns": 1768189932161422586,
    "size": 353,
    "sha256_12": "15952c921af7"
  },
  "conf/snapshot_templates.json": {
    "mtime_ns": 1768447778400377061,
    "size": 15659,
    "sha256_12": "c10dd0b0ad18"
  },
  "devtools/build_catalog.py": {
    "mtime_ns": 1768319277766440692,
    "size": 4189,
    "sha256_12": "bbfc33a27ce7"
  },
  "devtools/build_icons.py": {
    "mtime_ns": 1768899892430066649,
    "size": 29929,
    "sha256_12": "51fdeac1b40a"
  },
  "devtools/codemap.py": {
    "mtime_ns": 1768534644392156488,
    "size": 6312,
    "sha256_12": "fd216e4f7e67"
  },
  "devtools/hotfix_add_iconconfig.py": {
    "mtime_ns": 1768373102672331296,
    "size": 1994,
    "sha256_12": "8f05b39c1640"
  },
  "devtools/hotfix_add_write_png.py": {
    "mtime_ns": 1768372937214069297,
    "size": 1994,
    "sha256_12": "d6d6dc118a4b"
  },
  "devtools/installer.py": {
    "mtime_ns": 1768214588004842077,
    "size": 3586,
    "sha256_12": "b1feb4cd296f"
  },
  "devtools/pm.py": {
    "mtime_ns": 1768286926569629380,
    "size": 6674,
    "sha256_12": "a18caa6ebf79"
  },
  "devtools/reporter.py": {
    "mtime_ns": 1768534627462232108,
    "size": 4751,
    "sha256_12": "50594fb292b8"
  },
  "devtools/sampler.py": {
    "mtime_ns": 1768914373979324042,
    "size": 14614,
    "sha256_12": "44c1ca6632d6"
  },
  "devtools/serve_webcraft.py": {
    "mtime_ns": 1768895981485538619,
    "size": 6049,
    "sha256_12": "180c7d164d0a"
  },
  "devtools/snapshot.py": {
    "mtime_ns": 1768544094058507833,
    "size": 51404,
    "sha256_12": "6411307db9d8"
  },
  "devtools/snapshot_gui.py": {
    "mtime_ns": 1768914799033433982,
    "size": 66112,
    "sha256_12": "7940229d33ef"
  },
  "docs/WEBCRAFT_NETWORK_STACK.md": {
    "mtime_ns": 1768353772090295245,
    "size": 1583,
    "sha256_12": "ba49b13920f7"
  },
  "snaptxt": {
    "mtime_ns": 1768371731951445208,
    "size": 249258,
    "sha256_12": "a12603bc0edf"
  },
  "src/doctor.py": {
    "mtime_ns": 1768227155431669575,
    "size": 7012,
    "sha256_12": "69d9d480c023"
  },
  "src/explorer.py": {
    "mtime_ns": 1768318602127449894,
    "size": 9616,
    "sha256_12": "6f0febfb5667"
  },
  "src/klei_atlas_tex.py": {
    "mtime_ns": 1768370694412032911,
    "size": 17056,
    "sha256_12": "9e1cb85f9889"
  },
  "src/registry.py": {
    "mtime_ns": 1768287414259449076,
    "size": 2414,
    "sha256_12": "49f94a18019d"
  },
  "src/wiki.py": {
    "mtime_ns": 1768318601474452805,
    "size": 22283,
    "sha256_12": "98e8c40fe7ba"
  },
  "data/index/wagstaff_catalog_v1.json": {
    "mtime_ns": 1768360757509041904,
    "size": 1024820,
    "sha256_12": "c6a6a12d29eb"
  },
  "data/index/wagstaff_icon_index_v1.json": {
    "mtime_ns": 1768382392105608647,
    "size": 283080,
    "sha256_12": "1920da880bb9"
  },
  "README.md": {
    "mtime_ns": 1768921629453001822,
    "size": 4899,
    "sha256_12": "51d4e400a967"
  },
  "PROJECT_STATUS.json": {
    "mtime_ns": 1768287237635238708,
    "size": 1939,
    "sha256_12": "2abe53316639"
  },
  "src/guide.py": {
    "mtime_ns": 1768206472553194382,
    "size": 1548,
    "sha256_12": "b69213e54f5e"
  },
  "bin/Wagstaff-Lab": {
    "mtime_ns": 1768287436243350793,
    "size": 65,
    "sha256_12": "f7752ace0a59"
  },
  "bin/boot.sh": {
    "mtime_ns": 1768208092000948747,
    "size": 2250,
    "sha256_12": "524c5d2d4996"
  },
  "bin/dst_tool.sh": {
    "mtime_ns": 1768227697065247771,
    "size": 12532,
    "sha256_12": "a626b7bec4b0"
  },
  "bin/pm": {
    "mtime_ns": 1768287436244350789,
    "size": 67,
    "sha256_12": "c6931064b944"
  },
  "bin/wagstaff": {
    "mtime_ns": 1768287436244350789,
    "size": 824,
    "sha256_12": "f5b10da0f56e"
  },
  "data/reports/asset_registry.md": {
    "mtime_ns": 1768916590642461686,
    "size": 2096,
    "sha256_12": "45c762a51673"
  },
  "data/reports/catalog_summary.md": {
    "mtime_ns": 1768360757510041899,
    "size": 1347,
    "sha256_12": "0481f88118cd"
  },
  "data/reports/dst_codemap.json": {
    "mtime_ns": 1768284905787661888,
    "size": 9771,
    "sha256_12": "641dac300b3e"
  },
  "data/reports/dst_codemap.md": {
    "mtime_ns": 1768284905786661893,
    "size": 5196,
    "sha256_12": "bb7f66b78652"
  },
  "data/reports/recipe_distribution.md": {
    "mtime_ns": 1768916591336458598,
    "size": 1655,
    "sha256_12": "e177df3496c5"
  },
  "data/samples/samples_20260113_105500.manifest.json": {
    "mtime_ns": 1768272901158242553,
    "size": 3455,
    "sha256_12": "eb55230ae2c1"
  },
  "data/samples/samples_20260113_105500.md": {
    "mtime_ns": 1768272901157242557,
    "size": 98207,
    "sha256_12": "62a18d214507"
  },
  "data/samples/samples_20260113_112749.manifest.json": {
    "mtime_ns": 1768274869713432696,
    "size": 2006,
    "sha256_12": "b9f885cebc8a"
  },
  "data/samples/samples_20260113_112749.md": {
    "mtime_ns": 1768274869712432700,
    "size": 40900,
    "sha256_12": "0ecf222f76c5"
  },
  "tests/test_recipes.py": {
    "mtime_ns": 1768534842743270533,
    "size": 1653,
    "sha256_12": "c854302c4b59"
  },
  "src/webcraft/i18n_service.py": {
    "mtime_ns": 1768412628728756370,
    "size": 13300,
    "sha256_12": "f4643c37adb3"
  },
  "0001-webcraft-i18n-po-step3.patch": {
    "mtime_ns": 1768412588918933918,
    "size": 31610,
    "sha256_12": "8979c46dc2c2"
  },
  "src/webcraft/api.py.orig": {
    "mtime_ns": 1768447323189420727,
    "size": 16697,
    "sha256_12": "3c521c3a11c1"
  },
  "src/webcraft/app.py.orig": {
    "mtime_ns": 1768447101962413908,
    "size": 4801,
    "sha256_12": "cac1104c9c5b"
  },
  "src/webcraft/app.py.rej": {
    "mtime_ns": 1768447643255983801,
    "size": 514,
    "sha256_12": "882aba4c8d08"
  },
  "src/webcraft/ui.py.orig": {
    "mtime_ns": 1768447508571588470,
    "size": 76672,
    "sha256_12": "11522b38baed"
  },
  "src/webcraft/ui.py.rej": {
    "mtime_ns": 1768447643258983787,
    "size": 7754,
    "sha256_12": "3d0aed5da33b"
  },
  "0001-webcraft-i18n-po-v2.patch": {
    "mtime_ns": 1768447304797503305,
    "size": 27760,
    "sha256_12": "c1deddf0bfc3"
  },
  "docs/README.md": {
    "mtime_ns": 1768922528450007913,
    "size": 1002,
    "sha256_12": "c49ff2098dd4"
  },
  "docs/guides/DEV_GUIDE.md": {
    "mtime_ns": 1768922572566812166,
    "size": 11820,
    "sha256_12": "9bdf3a820c53"
  },
  "docs/management/ROADMAP.md": {
    "mtime_ns": 1768904574878157598,
    "size": 2099,
    "sha256_12": "40bb5fc18729"
  },
  "apps/cli/main.py": {
    "mtime_ns": 1768538902966128320,
    "size": 1747,
    "sha256_12": "1f13f3912194"
  },
  "apps/cli/registry.py": {
    "mtime_ns": 1768919212915774322,
    "size": 5733,
    "sha256_12": "bf4db21c5938"
  },
  "apps/__init__.py": {
    "mtime_ns": 1768534367565392961,
    "size": 52,
    "sha256_12": "358b6db47998"
  },
  "apps/cli/__init__.py": {
    "mtime_ns": 1768534367567392952,
    "size": 43,
    "sha256_12": "f8d7e7942c05"
  },
  "apps/cli/cli_common.py": {
    "mtime_ns": 1768535721493345490,
    "size": 1915,
    "sha256_12": "3ee63244bc5c"
  },
  "apps/cli/commands/__init__.py": {
    "mtime_ns": 1768534367568392948,
    "size": 51,
    "sha256_12": "6ea567813f48"
  },
  "apps/cli/commands/dash.py": {
    "mtime_ns": 1768922072037033005,
    "size": 11582,
    "sha256_12": "5b127fa90c44"
  },
  "apps/cli/commands/doctor.py": {
    "mtime_ns": 1768536617856341077,
    "size": 6232,
    "sha256_12": "9f344e461317"
  },
  "apps/cli/commands/explorer.py": {
    "mtime_ns": 1768898539233117660,
    "size": 9805,
    "sha256_12": "6d063399516d"
  },
  "apps/cli/commands/mgmt.py": {
    "mtime_ns": 1768917421923756742,
    "size": 7876,
    "sha256_12": "004cb61bd8a5"
  },
  "apps/cli/commands/server.py": {
    "mtime_ns": 1768542747142596892,
    "size": 209,
    "sha256_12": "6c94b0d9aa63"
  },
  "apps/cli/commands/wiki.py": {
    "mtime_ns": 1768898559623026378,
    "size": 22341,
    "sha256_12": "a442b723e453"
  },
  "apps/server/__init__.py": {
    "mtime_ns": 1768542607790213641,
    "size": 66,
    "sha256_12": "00130d1d4140"
  },
  "apps/server/cli.py": {
    "mtime_ns": 1768545275548177819,
    "size": 4691,
    "sha256_12": "8e414946c537"
  },
  "apps/server/config.py": {
    "mtime_ns": 1768542635485093171,
    "size": 2974,
    "sha256_12": "9ef01d91607b"
  },
  "apps/server/manager.py": {
    "mtime_ns": 1768545881110479258,
    "size": 7508,
    "sha256_12": "c7fa4e1b4e45"
  },
  "apps/server/ui.py": {
    "mtime_ns": 1768574416625812692,
    "size": 39402,
    "sha256_12": "6786f4b8ce07"
  },
  "apps/webcraft/__init__.py": {
    "mtime_ns": 1768534367570392939,
    "size": 48,
    "sha256_12": "43210b35acae"
  },
  "apps/webcraft/api.py": {
    "mtime_ns": 1768896067658151409,
    "size": 35980,
    "sha256_12": "92c2d565d4de"
  },
  "apps/webcraft/app.py": {
    "mtime_ns": 1768905862704399590,
    "size": 9336,
    "sha256_12": "0419bf41fdfd"
  },
  "apps/webcraft/catalog_store.py": {
    "mtime_ns": 1768906234834737514,
    "size": 59435,
    "sha256_12": "c4146e6d324a"
  },
  "apps/webcraft/cooking_planner.py": {
    "mtime_ns": 1768846094703500858,
    "size": 41532,
    "sha256_12": "db5056ac693c"
  },
  "apps/webcraft/i18n_index.py": {
    "mtime_ns": 1768642609713471920,
    "size": 4390,
    "sha256_12": "0fa925eef1c1"
  },
  "apps/webcraft/i18n_service.py": {
    "mtime_ns": 1768476198153879902,
    "size": 26143,
    "sha256_12": "28951d7fce69"
  },
  "apps/webcraft/icon_service.py": {
    "mtime_ns": 1768899881183116868,
    "size": 12077,
    "sha256_12": "96a6a2513eea"
  },
  "apps/webcraft/planner.py": {
    "mtime_ns": 1768353714947547458,
    "size": 3808,
    "sha256_12": "a9ac339eaf54"
  },
  "apps/webcraft/settings.py": {
    "mtime_ns": 1768557571208759961,
    "size": 919,
    "sha256_12": "57f5a4c92b56"
  },
  "apps/webcraft/tuning_trace.py": {
    "mtime_ns": 1768905820186589498,
    "size": 3858,
    "sha256_12": "0a796c1a7679"
  },
  "apps/webcraft/ui.py": {
    "mtime_ns": 1768727798667945401,
    "size": 1260,
    "sha256_12": "8082523ecd0a"
  },
  "core/__init__.py": {
    "mtime_ns": 1768534367561392979,
    "size": 61,
    "sha256_12": "ac551446262f"
  },
  "core/analyzer.py": {
    "mtime_ns": 1768617445693409006,
    "size": 53880,
    "sha256_12": "0237e6589e2c"
  },
  "core/craft_recipes.py": {
    "mtime_ns": 1768892892958451245,
    "size": 28217,
    "sha256_12": "651e3208046b"
  },
  "core/engine.py": {
    "mtime_ns": 1768900224170585401,
    "size": 16480,
    "sha256_12": "fec51fe8b91f"
  },
  "core/indexers/__init__.py": {
    "mtime_ns": 1768534367563392970,
    "size": 48,
    "sha256_12": "e7fb45ee44bb"
  },
  "core/indexers/catalog_index.py": {
    "mtime_ns": 1768535031679426646,
    "size": 7063,
    "sha256_12": "ea5d556592d6"
  },
  "core/indexers/catalog_v2.py": {
    "mtime_ns": 1768891796527369020,
    "size": 25945,
    "sha256_12": "e1330d4f874e"
  },
  "core/indexers/i18n_index.py": {
    "mtime_ns": 1768642584220585731,
    "size": 6512,
    "sha256_12": "e2e7d3de4162"
  },
  "core/indexers/resource_index.py": {
    "mtime_ns": 1768891809223312003,
    "size": 23514,
    "sha256_12": "26d106eaa728"
  },
  "core/indexers/shared.py": {
    "mtime_ns": 1768891768938492920,
    "size": 2067,
    "sha256_12": "20b8e9e42b9c"
  },
  "core/klei_atlas_tex.py": {
    "mtime_ns": 1768610608322833823,
    "size": 17536,
    "sha256_12": "14b3a7105299"
  },
  "core/schemas/__init__.py": {
    "mtime_ns": 1768534367564392966,
    "size": 47,
    "sha256_12": "54ea79a6fc22"
  },
  "core/schemas/catalog_v2.py": {
    "mtime_ns": 1768617540525987235,
    "size": 824,
    "sha256_12": "1dc18eed6fb8"
  },
  "core/schemas/meta.py": {
    "mtime_ns": 1768898457817482123,
    "size": 808,
    "sha256_12": "f3a5643f582b"
  },
  "core/tagging.py": {
    "mtime_ns": 1768475928832079283,
    "size": 5775,
    "sha256_12": "9c009d2318ee"
  },
  "core/utils.py": {
    "mtime_ns": 1768465872014881767,
    "size": 1041,
    "sha256_12": "d7d80440b8ab"
  },
  "devtools/__init__.py": {
    "mtime_ns": 1768534367572392930,
    "size": 48,
    "sha256_12": "730483be1b04"
  },
  "devtools/build_catalog_index.py": {
    "mtime_ns": 1768536626917300577,
    "size": 2031,
    "sha256_12": "4dd79b3fb540"
  },
  "devtools/build_catalog_v2.py": {
    "mtime_ns": 1768899949855810238,
    "size": 6479,
    "sha256_12": "af3b1c977d49"
  },
  "devtools/build_i18n_index.py": {
    "mtime_ns": 1768899949854810243,
    "size": 9722,
    "sha256_12": "adbc55ab6ae0"
  },
  "devtools/build_resource_index.py": {
    "mtime_ns": 1768899949855810238,
    "size": 5320,
    "sha256_12": "a47bde51cd90"
  },
  "devtools/catalog_quality.py": {
    "mtime_ns": 1768552395320299236,
    "size": 14996,
    "sha256_12": "7e13eec0b0fb"
  },
  "devtools/quality_gate.py": {
    "mtime_ns": 1768921040518627416,
    "size": 13291,
    "sha256_12": "ea888a6abf12"
  },
  "devtools/raw_scan.py": {
    "mtime_ns": 1768899949854810243,
    "size": 29214,
    "sha256_12": "4066504f9eac"
  },
  "data/reports/catalog_quality_report.md": {
    "mtime_ns": 1768921536830414761,
    "size": 3351,
    "sha256_12": "02158681fd99"
  },
  "data/reports/catalog_v2_summary.md": {
    "mtime_ns": 1768900144556940881,
    "size": 341,
    "sha256_12": "40df99deacde"
  },
  "docs/architecture/WEBCRAFT_NETWORK_STACK.md": {
    "mtime_ns": 1768905356546661403,
    "size": 1868,
    "sha256_12": "69134d3ef311"
  },
  "docs/guides/CLI_GUIDE.md": {
    "mtime_ns": 1768922582508768055,
    "size": 3291,
    "sha256_12": "e861f5485b74"
  },
  "docs/management/PROJECT_MANAGEMENT.md": {
    "mtime_ns": 1768921095685381474,
    "size": 5613,
    "sha256_12": "51a74bbf8cf3"
  },
  "docs/specs/CATALOG_V2_SPEC.md": {
    "mtime_ns": 1768905911525181539,
    "size": 11740,
    "sha256_12": "e57b140a47fc"
  },
  "devtools/build_catalog_sqlite.py": {
    "mtime_ns": 1768905801056674942,
    "size": 24035,
    "sha256_12": "31af5764fb1a"
  },
  "devtools/stats_gap_inspect.py": {
    "mtime_ns": 1768891838966178430,
    "size": 13516,
    "sha256_12": "99fce71b728c"
  },
  "data/reports/stats_gap_inspect.md": {
    "mtime_ns": 1768554129969350156,
    "size": 1124,
    "sha256_12": "e0eead6dd5a4"
  },
  "apps/cli/i18n.py": {
    "mtime_ns": 1768916290200798576,
    "size": 3712,
    "sha256_12": "c7ec26928806"
  },
  "apps/cli/mgmt_parser.py": {
    "mtime_ns": 1768917321125206122,
    "size": 2233,
    "sha256_12": "d17344d0fdfd"
  },
  "apps/webcraft/mechanism_store.py": {
    "mtime_ns": 1768907621090551645,
    "size": 15278,
    "sha256_12": "f247804f6708"
  },
  "core/assets/__init__.py": {
    "mtime_ns": 1768899916877957490,
    "size": 61,
    "sha256_12": "7ddf1961ae47"
  },
  "core/assets/klei_atlas_tex.py": {
    "mtime_ns": 1768610608322833823,
    "size": 17536,
    "sha256_12": "14b3a7105299"
  },
  "core/config/__init__.py": {
    "mtime_ns": 1768899936734868825,
    "size": 155,
    "sha256_12": "f66f248d1bf3"
  },
  "core/config/loader.py": {
    "mtime_ns": 1768899979760676712,
    "size": 1022,
    "sha256_12": "b40df7bcb20c"
  },
  "core/indexers/farming_defs.py": {
    "mtime_ns": 1768891803596337273,
    "size": 19303,
    "sha256_12": "c55f523da4ff"
  },
  "core/indexers/mechanism_index.py": {
    "mtime_ns": 1768907712398144319,
    "size": 16549,
    "sha256_12": "04943ae9991c"
  },
  "core/lua/__init__.py": {
    "mtime_ns": 1768891441465963664,
    "size": 1089,
    "sha256_12": "e0649c1b83f7"
  },
  "core/lua/call_extractor.py": {
    "mtime_ns": 1768891429389017901,
    "size": 5394,
    "sha256_12": "5588fec4b7be"
  },
  "core/lua/expr.py": {
    "mtime_ns": 1768891401298144052,
    "size": 4804,
    "sha256_12": "87b0d66a5bd5"
  },
  "core/lua/match.py": {
    "mtime_ns": 1768891371415278254,
    "size": 1691,
    "sha256_12": "786839bb2405"
  },
  "core/lua/scan.py": {
    "mtime_ns": 1768891335481439625,
    "size": 3332,
    "sha256_12": "19edc5ad75ae"
  },
  "core/lua/split.py": {
    "mtime_ns": 1768891357731339706,
    "size": 3617,
    "sha256_12": "bcd71d71a3c6"
  },
  "core/parsers/__init__.py": {
    "mtime_ns": 1768892276544214770,
    "size": 812,
    "sha256_12": "89fd1dc20368"
  },
  "core/parsers/base.py": {
    "mtime_ns": 1768891449746926473,
    "size": 540,
    "sha256_12": "68e9935d3a97"
  },
  "core/parsers/component.py": {
    "mtime_ns": 1768892271223238625,
    "size": 3047,
    "sha256_12": "880faae7031f"
  },
  "core/parsers/cooking.py": {
    "mtime_ns": 1768891736468638754,
    "size": 27295,
    "sha256_12": "33386ba348fc"
  },
  "core/parsers/loot.py": {
    "mtime_ns": 1768891465084857590,
    "size": 2175,
    "sha256_12": "3595dc46ca58"
  },
  "core/parsers/lua_analyzer.py": {
    "mtime_ns": 1768891517924620273,
    "size": 1623,
    "sha256_12": "cecaa2d581fa"
  },
  "core/parsers/prefab.py": {
    "mtime_ns": 1768891506161673103,
    "size": 3102,
    "sha256_12": "f08e0ff280ca"
  },
  "core/parsers/strings.py": {
    "mtime_ns": 1768891487552756680,
    "size": 610,
    "sha256_12": "bf621ad77af2"
  },
  "core/parsers/tuning.py": {
    "mtime_ns": 1768891579176345172,
    "size": 12559,
    "sha256_12": "e43dd5a73a7b"
  },
  "core/parsers/widget.py": {
    "mtime_ns": 1768891479893791079,
    "size": 575,
    "sha256_12": "ccd11e91cddd"
  },
  "core/version.py": {
    "mtime_ns": 1768898450097516683,
    "size": 1182,
    "sha256_12": "fd907b450742"
  },
  "devtools/build_cache.py": {
    "mtime_ns": 1768827884500661842,
    "size": 2553,
    "sha256_12": "dadaa666e6b2"
  },
  "devtools/build_farming_defs.py": {
    "mtime_ns": 1768899949853810247,
    "size": 3327,
    "sha256_12": "e8b2ff3ebd60"
  },
  "devtools/build_index_manifest.py": {
    "mtime_ns": 1768900339950068432,
    "size": 5866,
    "sha256_12": "b3087b84a361"
  },
  "devtools/build_mechanism_index.py": {
    "mtime_ns": 1768921048713590881,
    "size": 22780,
    "sha256_12": "75ed6486d405"
  },
  "devtools/portal_hub.py": {
    "mtime_ns": 1768918065650887348,
    "size": 24138,
    "sha256_12": "602f6d81f1a3"
  },
  "devtools/report_hub.py": {
    "mtime_ns": 1768919302172376547,
    "size": 24028,
    "sha256_12": "0c3c7791def8"
  },
  "devtools/report_utils.py": {
    "mtime_ns": 1768917299838301026,
    "size": 7650,
    "sha256_12": "8b2e940b23e4"
  },
  "devtools/validators.py": {
    "mtime_ns": 1768921030598671642,
    "size": 12630,
    "sha256_12": "3dd3a4cef1b1"
  },
  "data/reports/catalog_index_summary.md": {
    "mtime_ns": 1768900153995898735,
    "size": 198,
    "sha256_12": "58b64665db95"
  },
  "data/reports/dst_raw_coverage.md": {
    "mtime_ns": 1768916587833474185,
    "size": 12001,
    "sha256_12": "25bf603e5f6b"
  },
  "data/reports/mechanism_crosscheck_report.md": {
    "mtime_ns": 1768911818859870824,
    "size": 1824,
    "sha256_12": "f33209a4ec09"
  },
  "data/reports/mechanism_index_summary.md": {
    "mtime_ns": 1768911818855870842,
    "size": 821,
    "sha256_12": "7fcd5cd604ab"
  },
  "data/reports/quality_gate_report.md": {
    "mtime_ns": 1768921536628415662,
    "size": 1581,
    "sha256_12": "46feb9bc8059"
  },
  "data/reports/resource_index_summary.md": {
    "mtime_ns": 1768900106377111355,
    "size": 1247,
    "sha256_12": "495c92f7d778"
  },
  "docs/archived/COOKING_UPGRADE.md": {
    "mtime_ns": 1768618530886568896,
    "size": 2022,
    "sha256_12": "118ef24f1c4c"
  },
  "docs/archived/WEBCRAFT_UI_MODULARIZATION.md": {
    "mtime_ns": 1768653007829018730,
    "size": 2829,
    "sha256_12": "b7ef1f4059e6"
  },
  "docs/management/VNEXT_REFACTOR_PLAN.md": {
    "mtime_ns": 1768894299544128054,
    "size": 7679,
    "sha256_12": "5f3cbf715663"
  },
  "docs/management/WEBCRAFT_ATLAS_LEDGER_UI_REFACTOR.md": {
    "mtime_ns": 1768817202548268226,
    "size": 1395,
    "sha256_12": "45625a3ebd8b"
  },
  "docs/management/WEBCRAFT_MOBILE_APP_SHELL.md": {
    "mtime_ns": 1768670907544400747,
    "size": 2388,
    "sha256_12": "b93409358ae9"
  },
  "docs/specs/FARMING_MECHANICS_REPORT.md": {
    "mtime_ns": 1768878052631612510,
    "size": 4401,
    "sha256_12": "ea09674a3e8e"
  },
  "docs/specs/MECHANISM_INDEX_SPEC.md": {
    "mtime_ns": 1768907632331501494,
    "size": 3037,
    "sha256_12": "0c1e16905f63"
  },
  "docs/specs/SQLITE_V4_SPEC.md": {
    "mtime_ns": 1768907661365371976,
    "size": 7953,
    "sha256_12": "59fbc3f5852a"
  }
}
